{"title":"关键词检测模块acfilter更新了","zzzContent":"以前版本的<a href=\"http://github.com/xurenlu/acfilter\" target=\"_blank\">acfilter</a> 只能检测完整出现的敏感词;我对它做了升级，目前它支持对\"敏*感*词\"类似的关键词的检测.当然，会更慢一点。\n用法参见<a href=\"http://github.com/xurenlu/acfilter\">http://github.com/xurenlu/acfilter</a>的说明。acfilter_check_text函数现在支持第三个参数:max_seek,表明中间可间隔多少字符:\n\nprint_r(acfilter_check_text($ac,\"曾经有一个很狗***屎的部门,叫工\\信//部\",2));\n\n当第三个参数是2是能检测到工信部这个词,检测不到狗屎这个关键词。\n当第三个参数改成3,”工信部\"和“狗屎”都能检测到了。\n\n当然，我以为工信部不用加到关键词里去....祈祷您正确地使用它。","postDate":"2012-01-20 01:19:32","postId":"1213","type":"post","status":"draft","imported":true,"file":"1213.md"}